climetlab_maelstrom_radiation/__init__.py
climetlab_maelstrom_radiation/radiation.py
climetlab_maelstrom_radiation/radiation_tf.py
climetlab_maelstrom_radiation/benchmarks/__init__.py
climetlab_maelstrom_radiation/benchmarks/benchmarks_lw.py
climetlab_maelstrom_radiation/benchmarks/benchmarks_lw_inference.py
climetlab_maelstrom_radiation/benchmarks/benchmarks_sw.py
climetlab_maelstrom_radiation/benchmarks/benchmarks_sw_inference.py
climetlab_maelstrom_radiation/benchmarks/benchmarks_sw_inprog.py
climetlab_maelstrom_radiation/benchmarks/data.py
climetlab_maelstrom_radiation/benchmarks/dummy_model.py
climetlab_maelstrom_radiation/benchmarks/inp_max_norm.npy
climetlab_maelstrom_radiation/benchmarks/layers.py
climetlab_maelstrom_radiation/benchmarks/losses.py
climetlab_maelstrom_radiation/benchmarks/metrics.py
climetlab_maelstrom_radiation/benchmarks/models.py
climetlab_maelstrom_radiation/benchmarks/mycallbacks.py
climetlab_maelstrom_radiation/benchmarks/plotting.py
climetlab_maelstrom_radiation/benchmarks/utils.py
climetlab_maelstrom_radiation/benchmarks/visualise_models.py
climetlab_maelstrom_radiation-0.7.5.dist-info/LICENSE
climetlab_maelstrom_radiation-0.7.5.dist-info/METADATA
climetlab_maelstrom_radiation-0.7.5.dist-info/WHEEL
climetlab_maelstrom_radiation-0.7.5.dist-info/entry_points.txt
climetlab_maelstrom_radiation-0.7.5.dist-info/top_level.txt
climetlab_maelstrom_radiation-0.7.5.dist-info/zip-safe
climetlab_maelstrom_radiation-0.7.5.dist-info/RECORD
